README.md
setup.py
slidesgen/__init__.py
slidesgen/slidesgen.py
slidesgen.egg-info/PKG-INFO
slidesgen.egg-info/SOURCES.txt
slidesgen.egg-info/dependency_links.txt
slidesgen.egg-info/entry_points.txt
slidesgen.egg-info/requires.txt
slidesgen.egg-info/top_level.txt