Metadata-Version: 2.1
Name: slidesgen
Version: 0.2
Summary: A simple tool to generate slides from markdown files
Author: sjqzhang
